llm_station/__init__.py
llm_station/agent/runtime.py
llm_station/batch/__init__.py
llm_station/batch/anthropic_batch.py
llm_station/batch/google_batch.py
llm_station/batch/openai_batch.py
llm_station/cli/__init__.py
llm_station/cli/logging_cli.py
llm_station/logging/__init__.py
llm_station/logging/agent_logger.py
llm_station/models/__init__.py
llm_station/models/anthropic.py
llm_station/models/base.py
llm_station/models/google.py
llm_station/models/mock.py
llm_station/models/openai.py
llm_station/models/registry.py
llm_station/schemas/messages.py
llm_station/schemas/tooling.py
llm_station/tools/__init__.py
llm_station/tools/base.py
llm_station/tools/fetch_url.py
llm_station/tools/json_format.py
llm_station/tools/registry.py
llm_station/tools/code_execution/__init__.py
llm_station/tools/code_execution/anthropic.py
llm_station/tools/code_execution/google.py
llm_station/tools/code_execution/openai.py
llm_station/tools/image_generation/__init__.py
llm_station/tools/image_generation/google.py
llm_station/tools/image_generation/openai.py
llm_station/tools/url_context/__init__.py
llm_station/tools/url_context/google.py
llm_station/tools/web_fetch/__init__.py
llm_station/tools/web_fetch/anthropic.py
llm_station/tools/web_search/__init__.py
llm_station/tools/web_search/anthropic.py
llm_station/tools/web_search/google.py
llm_station/tools/web_search/openai.py
llm_station-1.0.1.dist-info/licenses/LICENSE
llm_station-1.0.1.dist-info/METADATA
llm_station-1.0.1.dist-info/WHEEL
llm_station-1.0.1.dist-info/top_level.txt
llm_station-1.0.1.dist-info/RECORD
