Metadata-Version: 2.4
Name: llm-station
Version: 1.0.1
Summary: Agent framework with tool calling for OpenAI, Anthropic, and Google
Author: Izhar Ali
License-Expression: MIT
Project-URL: Homepage, https://github.com/ali-izhar/llm-station
Project-URL: Bug Reports, https://github.com/ali-izhar/llm-station/issues
Project-URL: Source, https://github.com/ali-izhar/llm-station
Project-URL: Documentation, https://github.com/ali-izhar/llm-station#readme
Keywords: llm,agents,tools,openai,anthropic,gemini,smart-tools,ai,chatgpt,claude,gemini
Classifier: Development Status :: 5 - Production/Stable
Classifier: Intended Audience :: Developers
Classifier: Topic :: Software Development :: Libraries :: Python Modules
Classifier: Topic :: Scientific/Engineering :: Artificial Intelligence
Classifier: Programming Language :: Python :: 3
Classifier: Programming Language :: Python :: 3.9
Classifier: Programming Language :: Python :: 3.10
Classifier: Programming Language :: Python :: 3.11
Classifier: Programming Language :: Python :: 3.12
Classifier: Operating System :: OS Independent
Requires-Python: >=3.9
License-File: LICENSE
Requires-Dist: python-dotenv>=1.0.0
Provides-Extra: openai
Requires-Dist: openai>=1.40.0; extra == "openai"
Provides-Extra: anthropic
Requires-Dist: anthropic>=0.31.0; extra == "anthropic"
Provides-Extra: google
Requires-Dist: google-genai>=0.3.0; extra == "google"
Provides-Extra: all
Requires-Dist: openai>=1.40.0; extra == "all"
Requires-Dist: anthropic>=0.31.0; extra == "all"
Requires-Dist: google-genai>=0.3.0; extra == "all"
Provides-Extra: dev
Requires-Dist: pytest>=7.2; extra == "dev"
Requires-Dist: python-dotenv>=1.0.0; extra == "dev"
Requires-Dist: openai>=1.40.0; extra == "dev"
Requires-Dist: anthropic>=0.31.0; extra == "dev"
Requires-Dist: google-genai>=0.3.0; extra == "dev"
Dynamic: license-file
